MANIFEST.in
README
runtask.py
setup.cfg
setup.py
doc/changelog.rst
doc/conf.py
doc/contents.rst
doc/examples.rst
doc/exectiming.rst
doc/index.rst
doc/intro.rst
doc/moduleref.rst
doc/tasks.rst
examples/.directory
examples/contents.rst
examples/event.out
examples/event.py
examples/example.out
examples/example.py
examples/lock.out
examples/lock.py
examples/runtask.py
examples/semaphore.out
examples/semaphore.py
examples/timecap.out
examples/timecap.py
runtask.egg-info/PKG-INFO
runtask.egg-info/SOURCES.txt
runtask.egg-info/dependency_links.txt
runtask.egg-info/top_level.txt