Metadata-Version: 1.1
Name: runtask
Version: 0.5.0
Summary: RunTask is a coherent time task scheduler
Home-page: http://opendcf77.inrim.it/runtask
Author: Fabrizio Pollastri
Author-email: f.pollastri@inrim.it
License: http://www.gnu.org/licenses/gpl.txt
Download-URL: https://testpypi.python.org/simple/runtask
Platform: Linux
Classifier: Development Status :: 3 - Alpha
Classifier: Intended Audience :: Developers
Classifier: License :: OSI Approved :: GNU General Public License (GPL)
Classifier: Programming Language :: Python
Classifier: Topic :: Scientific/Engineering
Classifier: Topic :: Software Development :: Libraries :: Python Modules
Classifier: Operating System :: POSIX :: Linux
